<clickhouse>
 <!-- Don't keep logs forever -->
 <asynchronous_metric_log>
  <ttl>event_date + INTERVAL 30 DAY DELETE</ttl>
 </asynchronous_metric_log>
 <metric_log>
  <ttl>event_date + INTERVAL 30 DAY DELETE</ttl>
 </metric_log>
 <part_log>
  <ttl>event_date + INTERVAL 30 DAY DELETE</ttl>
 </part_log>
 <query_log>
  <ttl>event_date + INTERVAL 30 DAY DELETE</ttl>
 </query_log>
 <query_thread_log>
  <ttl>event_date + INTERVAL 30 DAY DELETE</ttl>
 </query_thread_log>
 <trace_log>
  <ttl>event_date + INTERVAL 30 DAY DELETE</ttl>
 </trace_log>
 <!-- Enable Prometheus endpoint -->
 <prometheus>
  <endpoint>/metrics</endpoint>
  <metrics>true</metrics>
  <events>true</events>
  <asynchronous_metrics>true</asynchronous_metrics>
 </prometheus>
 <logger>
   <level>information</level>
 </logger>
</clickhouse>
